{"name":"searching_by_keyword_pear_should_display_the_corresponding_article","id":"org.example.features.search.SearchByKeywordStory:searching_by_keyword_pear_should_display_the_corresponding_article","testCaseName":"org.example.features.search.SearchByKeywordStory","testSteps":[{"number":1,"description":"Is the home page","duration":591,"startTime":"2024-04-22T08:20:21.975109900+03:00[Europe/Bucharest]","screenshots":[{"screenshot":"4063c5a33e1e705b49f959b96e6ad60c198e59746299923e8679e5a0c689166a.png","timeStamp":1713763222164},{"screenshot":"edd570cf91317d8e926c28b6b0b0465093c5df67b6f959f3b5c1e224586efbc4.png","timeStamp":1713763222567}],"result":"SUCCESS","precondition":false,"level":0},{"number":2,"description":"Looks for: pear","duration":1387,"startTime":"2024-04-22T08:20:22.568035200+03:00[Europe/Bucharest]","screenshots":[{"screenshot":"769a60f58bc2c3d6b1d16096a93d083aee3b9f35565c7cb5bce3072373358572.png","timeStamp":1713763223955}],"result":"SUCCESS","precondition":false,"level":0,"children":[{"number":3,"description":"Enters: pear","duration":452,"startTime":"2024-04-22T08:20:22.570017500+03:00[Europe/Bucharest]","screenshots":[{"screenshot":"d69e4f78b6c2c2d6fbe5ebc415dd9b160f1fd6f947078103608c5927f265517c.png","timeStamp":1713763223021}],"result":"SUCCESS","precondition":false,"level":1},{"number":4,"description":"Starts search","duration":930,"startTime":"2024-04-22T08:20:23.022539900+03:00[Europe/Bucharest]","screenshots":[{"screenshot":"d69e4f78b6c2c2d6fbe5ebc415dd9b160f1fd6f947078103608c5927f265517c.png","timeStamp":1713763223024},{"screenshot":"769a60f58bc2c3d6b1d16096a93d083aee3b9f35565c7cb5bce3072373358572.png","timeStamp":1713763223953}],"result":"SUCCESS","precondition":false,"level":1}]},{"number":5,"description":"Should see definition: An edible fruit produced by the pear tree, similar to an apple but typically elongated towards the stem.","duration":233,"startTime":"2024-04-22T08:20:23.956261600+03:00[Europe/Bucharest]","screenshots":[{"screenshot":"81db3205c60369e6cca36f6d821e376b57085e715621fd64814bcab3ef8d76c9.png","timeStamp":1713763224189}],"result":"SUCCESS","precondition":false,"level":0}],"userStory":{"id":"org.example.features.search.SearchByKeywordStory","storyName":"Search by keyword story","storyClassName":"org.example.features.search.SearchByKeywordStory","path":"search","type":"story"},"featureTag":{"name":"Search/Search by keyword story","type":"story","displayName":"Search/Search by keyword story"},"title":"Searching by keyword pear should display the corresponding article","tags":[{"name":"Search","type":"feature","displayName":"Search"},{"name":"Search/Search by keyword story","type":"story","displayName":"Search/Search by keyword story"},{"name":"Search","type":"capability","displayName":"Search for definitions"}],"startTime":"2024-04-22T08:20:21.860535600+03:00[Europe/Bucharest]","duration":2328,"projectKey":"","sessionId":"5b5c5571c6ba9ad213499359dc3d7095","driver":"chrome","isManualTestingUpToDate":false,"manual":false,"testSource":"JUnit","order":0,"result":"SUCCESS"}